{"nodes": [{"id": "permission_service_service", "label": "permission.Service (interface)", "file_type": "code", "source_file": "internal/core/permission/service.go", "source_location": "8", "source_url": null, "captured_at": null, "author": null, "contributor": null}, {"id": "permission_service_serviceimpl", "label": "permission.service (struct)", "file_type": "code", "source_file": "internal/core/permission/service.go", "source_location": "16", "source_url": null, "captured_at": null, "author": null, "contributor": null}], "edges": [{"source": "permission_service_serviceimpl", "target": "permission_service_service", "relation": "implements", "confidence": "EXTRACTED", "confidence_score": 1.0, "source_file": "internal/core/permission/service.go", "source_location": "16", "weight": 1.0}, {"source": "permission_service_serviceimpl", "target": "permission_repository_repository", "relation": "references", "confidence": "EXTRACTED", "confidence_score": 1.0, "source_file": "internal/core/permission/service.go", "source_location": "17", "weight": 1.0}, {"source": "permission_service_serviceimpl", "target": "permission_dto_permissionresponse", "relation": "references", "confidence": "EXTRACTED", "confidence_score": 1.0, "source_file": "internal/core/permission/service.go", "source_location": "56", "weight": 1.0}, {"source": "permission_service_service", "target": "role_service_service", "relation": "semantically_similar_to", "confidence": "INFERRED", "confidence_score": 0.85, "source_file": "internal/core/permission/service.go", "source_location": null, "weight": 1.0}], "hyperedges": []}